pytkfaicons/__init__.py
pytkfaicons/__main__.py
pytkfaicons/const.py
pytkfaicons/conv.py
pytkfaicons/fonts.py
pytkfaicons/main.py
pytkfaicons/fonts-dir/LICENSE-font-awesome.txt
pytkfaicons/fonts-dir/__init__.py
pytkfaicons/fonts-dir/fa-brands-400.ttf
pytkfaicons/fonts-dir/fa-regular-400.ttf
pytkfaicons/fonts-dir/fa-solid-900.ttf
pytkfaicons/fonts-dir/fa-v4compatibility.ttf
pytkfaicons/fonts-dir/icons.json
pytkfaicons-0.0.11.dist-info/LICENSE.md
pytkfaicons-0.0.11.dist-info/METADATA
pytkfaicons-0.0.11.dist-info/WHEEL
pytkfaicons-0.0.11.dist-info/top_level.txt
pytkfaicons-0.0.11.dist-info/RECORD
