Metadata-Version: 2.1
Name: pytkfaicons
Version: 0.0.11
Summary: tkinter fontawesome icons
Home-page: https://github.com/kr-g/pytkfaicons
Author: k. goger
Author-email: k.r.goger+pytkfaicons@gmail.com
License: others
Keywords: python tkinter fontawesome icons svg fonts
Platform: UNKNOWN
Classifier: Development Status :: 3 - Alpha
Classifier: Operating System :: POSIX :: Linux
Classifier: Operating System :: OS Independent
Classifier: Environment :: Console
Classifier: Intended Audience :: Developers
Classifier: Programming Language :: Python :: 3
Requires-Python: >=3.10
License-File: LICENSE.md
Requires-Dist: Pillow
